[
  {
    "id": "348727b7d3019074",
    "name": "Genesis Signs & Print",
    "company": "Genesis Signs & Print",
    "email": "",
    "phone": "",
    "location": "",
    "website": "",
    "source": "google_maps",
    "scrapedAt": "2026-03-24T13:39:39.619Z"
  },
  {
    "id": "886b901e9e368682",
    "name": "AURELIUS DIGITAL LTD",
    "company": "AURELIUS DIGITAL LTD",
    "email": "",
    "phone": "",
    "location": "",
    "website": "",
    "source": "google_maps",
    "scrapedAt": "2026-03-24T13:39:39.621Z"
  },
  {
    "id": "591a467c8051191b",
    "name": "Ave",
    "company": "Ave",
    "email": "",
    "phone": "",
    "location": "",
    "website": "",
    "source": "google_maps",
    "scrapedAt": "2026-03-24T13:39:39.622Z"
  },
  {
    "id": "23ec1c8577e47b42",
    "name": "Freelance Graphic Designer",
    "company": "Freelance Graphic Designer",
    "email": "",
    "phone": "",
    "location": "",
    "website": "",
    "source": "google_maps",
    "scrapedAt": "2026-03-24T13:39:39.623Z"
  },
  {
    "id": "494cd6f6e174c077",
    "name": "JM Graphic Design",
    "company": "JM Graphic Design",
    "email": "",
    "phone": "",
    "location": "",
    "website": "",
    "source": "google_maps",
    "scrapedAt": "2026-03-24T13:39:39.624Z"
  },
  {
    "id": "24d7e9e8ada48268",
    "name": "Shoreditch Design",
    "company": "Shoreditch Design",
    "email": "",
    "phone": "",
    "location": "",
    "website": "",
    "source": "google_maps",
    "scrapedAt": "2026-03-24T13:39:39.624Z"
  },
  {
    "id": "d42894a9bf6af2a3",
    "name": "Creative Harmony",
    "company": "Creative Harmony",
    "email": "",
    "phone": "",
    "location": "",
    "website": "",
    "source": "google_maps",
    "scrapedAt": "2026-03-24T13:39:39.624Z"
  },
  {
    "id": "3a195656c92edc4a",
    "name": "Graphic Design London",
    "company": "Graphic Design London",
    "email": "",
    "phone": "",
    "location": "",
    "website": "",
    "source": "google_maps",
    "scrapedAt": "2026-03-24T13:39:39.624Z"
  },
  {
    "id": "8f6e464c1ae8c658",
    "name": "Reactive",
    "company": "Reactive",
    "email": "",
    "phone": "",
    "location": "",
    "website": "",
    "source": "google_maps",
    "scrapedAt": "2026-03-24T13:39:39.625Z"
  },
  {
    "id": "71f3db9eca2bc9d1",
    "name": "Pelekan Design",
    "company": "Pelekan Design",
    "email": "",
    "phone": "",
    "location": "",
    "website": "",
    "source": "google_maps",
    "scrapedAt": "2026-03-24T13:39:39.625Z"
  },
  {
    "id": "51b64e75d9b0b4fc",
    "name": "WRB Design",
    "company": "WRB Design",
    "email": "",
    "phone": "",
    "location": "",
    "website": "",
    "source": "google_maps",
    "scrapedAt": "2026-03-24T13:39:39.626Z"
  },
  {
    "id": "1504e51092b96a8f",
    "name": "Crunch Design",
    "company": "Crunch Design",
    "email": "",
    "phone": "",
    "location": "",
    "website": "",
    "source": "google_maps",
    "scrapedAt": "2026-03-24T13:39:39.626Z"
  },
  {
    "id": "dd757e9a2eb58905",
    "name": "Graphic Kitchen | Hospitality | Restaurant & Hotel Branding | Digital Marketing | TripAdvisor Workshops in London",
    "company": "Graphic Kitchen | Hospitality | Restaurant & Hotel Branding | Digital Marketing | TripAdvisor Workshops in London",
    "email": "",
    "phone": "",
    "location": "",
    "website": "",
    "source": "google_maps",
    "scrapedAt": "2026-03-24T13:39:39.626Z"
  },
  {
    "id": "7939250868d135df",
    "name": "Make it Clear",
    "company": "Make it Clear",
    "email": "",
    "phone": "",
    "location": "",
    "website": "",
    "source": "google_maps",
    "scrapedAt": "2026-03-24T13:39:39.627Z"
  },
  {
    "id": "7f9643b30e07e2af",
    "name": "Xtream Design & Marketing",
    "company": "Xtream Design & Marketing",
    "email": "",
    "phone": "",
    "location": "",
    "website": "",
    "source": "google_maps",
    "scrapedAt": "2026-03-24T13:39:39.627Z"
  },
  {
    "id": "230e52717cef461f",
    "name": "Graphics Monkey",
    "company": "Graphics Monkey",
    "email": "",
    "phone": "",
    "location": "",
    "website": "",
    "source": "google_maps",
    "scrapedAt": "2026-03-24T13:39:39.628Z"
  },
  {
    "id": "c5563d2c6df2fa34",
    "name": "Deep",
    "company": "Deep",
    "email": "",
    "phone": "",
    "location": "",
    "website": "",
    "source": "google_maps",
    "scrapedAt": "2026-03-24T13:39:39.628Z"
  },
  {
    "id": "4ed55b38fe1ae98f",
    "name": "Top Left Design",
    "company": "Top Left Design",
    "email": "",
    "phone": "",
    "location": "",
    "website": "",
    "source": "google_maps",
    "scrapedAt": "2026-03-24T13:39:39.628Z"
  },
  {
    "id": "1603c997341f0100",
    "name": "surgery creations",
    "company": "surgery creations",
    "email": "",
    "phone": "",
    "location": "",
    "website": "",
    "source": "google_maps",
    "scrapedAt": "2026-03-24T13:39:39.629Z"
  },
  {
    "id": "a93aae3560a4a334",
    "name": "Graphic Designer London",
    "company": "Graphic Designer London",
    "email": "",
    "phone": "",
    "location": "",
    "website": "",
    "source": "google_maps",
    "scrapedAt": "2026-03-24T13:39:39.629Z"
  },
  {
    "id": "c314e8952b9056e7",
    "name": "Lyons Creative",
    "company": "Lyons Creative",
    "email": "",
    "phone": "",
    "location": "",
    "website": "",
    "source": "google_maps",
    "scrapedAt": "2026-03-24T13:39:39.630Z"
  },
  {
    "id": "5c7adeecafba4387",
    "name": "Plan B Creative Studio",
    "company": "Plan B Creative Studio",
    "email": "",
    "phone": "",
    "location": "",
    "website": "",
    "source": "google_maps",
    "scrapedAt": "2026-03-24T13:39:39.630Z"
  },
  {
    "id": "f3a5728c5de213e5",
    "name": "London Graphics Printing & Signage",
    "company": "London Graphics Printing & Signage",
    "email": "",
    "phone": "",
    "location": "",
    "website": "",
    "source": "google_maps",
    "scrapedAt": "2026-03-24T13:39:39.631Z"
  },
  {
    "id": "a57507fea9c75dbb",
    "name": "Habitat Cafe",
    "company": "Habitat Cafe",
    "email": "",
    "phone": "",
    "location": "",
    "website": "",
    "source": "google_maps",
    "scrapedAt": "2026-03-24T14:27:56.164Z"
  },
  {
    "id": "5d66b85d28d66c92",
    "name": "Roast CCX - Coffee & Culinary Xperience",
    "company": "Roast CCX - Coffee & Culinary Xperience",
    "email": "",
    "phone": "",
    "location": "",
    "website": "",
    "source": "google_maps",
    "scrapedAt": "2026-03-24T14:27:56.166Z"
  },
  {
    "id": "15c6ba65005d0970",
    "name": "Roast 24 Seven",
    "company": "Roast 24 Seven",
    "email": "",
    "phone": "",
    "location": "",
    "website": "",
    "source": "google_maps",
    "scrapedAt": "2026-03-24T14:27:56.167Z"
  },
  {
    "id": "3f994ca9efacb973",
    "name": "Concu Jubilee Hills",
    "company": "Concu Jubilee Hills",
    "email": "",
    "phone": "",
    "location": "",
    "website": "",
    "source": "google_maps",
    "scrapedAt": "2026-03-24T14:27:56.169Z"
  },
  {
    "id": "23b8a3b9a43c82f7",
    "name": "Roastery Coffee House",
    "company": "Roastery Coffee House",
    "email": "",
    "phone": "",
    "location": "",
    "website": "",
    "source": "google_maps",
    "scrapedAt": "2026-03-24T14:27:56.169Z"
  },
  {
    "id": "d910669147b0b199",
    "name": "Mirosa Cafe & Kitchen",
    "company": "Mirosa Cafe & Kitchen",
    "email": "",
    "phone": "",
    "location": "",
    "website": "",
    "source": "google_maps",
    "scrapedAt": "2026-03-24T14:27:56.170Z"
  },
  {
    "id": "4ce383939c0c2a86",
    "name": "BEL POSTO THE CAFE",
    "company": "BEL POSTO THE CAFE",
    "email": "",
    "phone": "",
    "location": "",
    "website": "",
    "source": "google_maps",
    "scrapedAt": "2026-03-24T14:27:56.171Z"
  },
  {
    "id": "f2866fda0cea90eb",
    "name": "The Grind Cafe",
    "company": "The Grind Cafe",
    "email": "",
    "phone": "",
    "location": "",
    "website": "",
    "source": "google_maps",
    "scrapedAt": "2026-03-24T14:27:56.172Z"
  },
  {
    "id": "687ce15bddbff567",
    "name": "The Story Cafe",
    "company": "The Story Cafe",
    "email": "",
    "phone": "",
    "location": "",
    "website": "",
    "source": "google_maps",
    "scrapedAt": "2026-03-24T14:27:56.173Z"
  },
  {
    "id": "90a316096b32dd66",
    "name": "Lé Vantage Café Bar",
    "company": "Lé Vantage Café Bar",
    "email": "",
    "phone": "",
    "location": "",
    "website": "",
    "source": "google_maps",
    "scrapedAt": "2026-03-24T14:27:56.174Z"
  },
  {
    "id": "63ed04b8b018234a",
    "name": "Lemerian Workin Cafe",
    "company": "Lemerian Workin Cafe",
    "email": "",
    "phone": "",
    "location": "",
    "website": "",
    "source": "google_maps",
    "scrapedAt": "2026-03-24T14:27:56.175Z"
  },
  {
    "id": "31e971957a2d41eb",
    "name": "ASTER CAFE & KITCHEN",
    "company": "ASTER CAFE & KITCHEN",
    "email": "",
    "phone": "",
    "location": "",
    "website": "",
    "source": "google_maps",
    "scrapedAt": "2026-03-24T14:27:56.176Z"
  },
  {
    "id": "c590e93067cd82de",
    "name": "Ce La Vie The Roof Top cafe",
    "company": "Ce La Vie The Roof Top cafe",
    "email": "",
    "phone": "",
    "location": "",
    "website": "",
    "source": "google_maps",
    "scrapedAt": "2026-03-24T14:27:56.177Z"
  },
  {
    "id": "839b2df64a2032c8",
    "name": "Motown Stories Cafe",
    "company": "Motown Stories Cafe",
    "email": "",
    "phone": "",
    "location": "",
    "website": "",
    "source": "google_maps",
    "scrapedAt": "2026-03-24T14:27:56.178Z"
  },
  {
    "id": "7049c18b7ad77954",
    "name": "SAGE Farm Cafe",
    "company": "SAGE Farm Cafe",
    "email": "",
    "phone": "",
    "location": "",
    "website": "",
    "source": "google_maps",
    "scrapedAt": "2026-03-24T14:27:56.179Z"
  },
  {
    "id": "813cf57e99a17cda",
    "name": "The Hole In The Wall Cafe",
    "company": "The Hole In The Wall Cafe",
    "email": "",
    "phone": "",
    "location": "",
    "website": "",
    "source": "google_maps",
    "scrapedAt": "2026-03-24T14:27:56.179Z"
  },
  {
    "id": "f20fe21b1d19771f",
    "name": "Autumn Leaf Cafe",
    "company": "Autumn Leaf Cafe",
    "email": "",
    "phone": "",
    "location": "",
    "website": "",
    "source": "google_maps",
    "scrapedAt": "2026-03-24T14:27:56.180Z"
  },
  {
    "id": "58b6380a22f43977",
    "name": "Van Lavino Cafe & Patisserie - Jubilee Hills",
    "company": "Van Lavino Cafe & Patisserie - Jubilee Hills",
    "email": "",
    "phone": "",
    "location": "",
    "website": "",
    "source": "google_maps",
    "scrapedAt": "2026-03-24T14:27:56.182Z"
  },
  {
    "id": "f8a9e2749206b600",
    "name": "Destination Cafe - Best Cafe in KPHB",
    "company": "Destination Cafe - Best Cafe in KPHB",
    "email": "",
    "phone": "",
    "location": "",
    "website": "",
    "source": "google_maps",
    "scrapedAt": "2026-03-24T14:27:56.183Z"
  },
  {
    "id": "ae057c3348e5991e",
    "name": "Rénao - Café | Bistro",
    "company": "Rénao - Café | Bistro",
    "email": "",
    "phone": "",
    "location": "",
    "website": "",
    "source": "google_maps",
    "scrapedAt": "2026-03-24T14:27:56.184Z"
  },
  {
    "id": "02eec0c2cc7a769e",
    "name": "The Coffee Cup - Kompally",
    "company": "The Coffee Cup - Kompally",
    "email": "",
    "phone": "",
    "location": "",
    "website": "",
    "source": "google_maps",
    "scrapedAt": "2026-03-24T14:28:33.647Z"
  },
  {
    "id": "7432f4781a491fb4",
    "name": "OTC - kompally, Old Trees Cafe, Hyderabad",
    "company": "OTC - kompally, Old Trees Cafe, Hyderabad",
    "email": "",
    "phone": "",
    "location": "",
    "website": "",
    "source": "google_maps",
    "scrapedAt": "2026-03-24T14:28:33.648Z"
  },
  {
    "id": "aff1170c9f1f6c2d",
    "name": "TRUE BLACK speciality coffee | Kompally",
    "company": "TRUE BLACK speciality coffee | Kompally",
    "email": "",
    "phone": "",
    "location": "",
    "website": "",
    "source": "google_maps",
    "scrapedAt": "2026-03-24T14:28:33.649Z"
  },
  {
    "id": "ef0adb8245c8c3ed",
    "name": "Huts & Hive - Bar and Restaurant",
    "company": "Huts & Hive - Bar and Restaurant",
    "email": "",
    "phone": "",
    "location": "",
    "website": "",
    "source": "google_maps",
    "scrapedAt": "2026-03-24T14:28:33.650Z"
  },
  {
    "id": "e889532c8bb72cf5",
    "name": "Kanchi Cafe - Kompally",
    "company": "Kanchi Cafe - Kompally",
    "email": "",
    "phone": "",
    "location": "",
    "website": "",
    "source": "google_maps",
    "scrapedAt": "2026-03-24T14:28:33.651Z"
  },
  {
    "id": "63d716f8a53ca6d0",
    "name": "L'unico Cafe",
    "company": "L'unico Cafe",
    "email": "",
    "phone": "",
    "location": "",
    "website": "",
    "source": "google_maps",
    "scrapedAt": "2026-03-24T14:28:33.653Z"
  },
  {
    "id": "8aa26b7def6bb777",
    "name": "The Funnel Hill Creamery",
    "company": "The Funnel Hill Creamery",
    "email": "",
    "phone": "",
    "location": "",
    "website": "",
    "source": "google_maps",
    "scrapedAt": "2026-03-24T14:28:33.654Z"
  },
  {
    "id": "28668f53fb7c965e",
    "name": "ALA the terrace lounge.",
    "company": "ALA the terrace lounge.",
    "email": "",
    "phone": "",
    "location": "",
    "website": "",
    "source": "google_maps",
    "scrapedAt": "2026-03-24T14:28:33.655Z"
  },
  {
    "id": "006701a34c882ffc",
    "name": "Whistling Brew",
    "company": "Whistling Brew",
    "email": "",
    "phone": "",
    "location": "",
    "website": "",
    "source": "google_maps",
    "scrapedAt": "2026-03-24T14:28:33.655Z"
  },
  {
    "id": "7e1953f98577724c",
    "name": "Lost Origin Coffee House",
    "company": "Lost Origin Coffee House",
    "email": "",
    "phone": "",
    "location": "",
    "website": "",
    "source": "google_maps",
    "scrapedAt": "2026-03-24T14:28:33.657Z"
  },
  {
    "id": "8e4977e881e162cd",
    "name": "Kapoor's Cafe - Kompally",
    "company": "Kapoor's Cafe - Kompally",
    "email": "",
    "phone": "",
    "location": "",
    "website": "",
    "source": "google_maps",
    "scrapedAt": "2026-03-24T14:28:33.659Z"
  },
  {
    "id": "4dd6b104113efb30",
    "name": "Ahoy Resto",
    "company": "Ahoy Resto",
    "email": "",
    "phone": "",
    "location": "",
    "website": "",
    "source": "google_maps",
    "scrapedAt": "2026-03-24T14:28:33.661Z"
  },
  {
    "id": "67676a035380b3a8",
    "name": "Cafe Anvika | Kompally",
    "company": "Cafe Anvika | Kompally",
    "email": "",
    "phone": "",
    "location": "",
    "website": "",
    "source": "google_maps",
    "scrapedAt": "2026-03-24T14:28:33.662Z"
  },
  {
    "id": "e340da04e2f15ac7",
    "name": "Starbucks",
    "company": "Starbucks",
    "email": "",
    "phone": "",
    "location": "",
    "website": "",
    "source": "google_maps",
    "scrapedAt": "2026-03-24T14:28:33.663Z"
  },
  {
    "id": "1a43120f811a1c71",
    "name": "O'Rica | Tropical Kitchen",
    "company": "O'Rica | Tropical Kitchen",
    "email": "",
    "phone": "",
    "location": "",
    "website": "",
    "source": "google_maps",
    "scrapedAt": "2026-03-24T14:28:33.664Z"
  },
  {
    "id": "d2bec270335d0e54",
    "name": "Cafe 360",
    "company": "Cafe 360",
    "email": "",
    "phone": "",
    "location": "",
    "website": "",
    "source": "google_maps",
    "scrapedAt": "2026-03-24T14:28:33.666Z"
  },
  {
    "id": "97aa454b4ae98426",
    "name": "R KAFE",
    "company": "R KAFE",
    "email": "",
    "phone": "",
    "location": "",
    "website": "",
    "source": "google_maps",
    "scrapedAt": "2026-03-24T14:28:33.668Z"
  },
  {
    "id": "b96f4a40e31508db",
    "name": "Minerva Coffee Shop",
    "company": "Minerva Coffee Shop",
    "email": "",
    "phone": "",
    "location": "",
    "website": "",
    "source": "google_maps",
    "scrapedAt": "2026-03-24T14:28:33.668Z"
  },
  {
    "id": "1a5d99b507411e81",
    "name": "Meta V Co-workspace",
    "company": "Meta V Co-workspace",
    "email": "",
    "phone": "",
    "location": "",
    "website": "",
    "source": "google_maps",
    "scrapedAt": "2026-03-24T14:28:33.669Z"
  }
]